puppet_es-0.8.1.dist-info/RECORD
puppet_es-0.8.1.dist-info/METADATA
puppet_es-0.8.1.dist-info/DESCRIPTION.rst
puppet_es-0.8.1.dist-info/top_level.txt
puppet_es-0.8.1.dist-info/WHEEL
puppet_es-0.8.1.dist-info/metadata.json
puppet_es-0.8.1.dist-info/entry_points.txt
puppet_es-0.8.1.dist-info/pbr.json
puppet_es/__init__.py
