Metadata-Version: 2.0
Name: puppet-es
Version: 0.8.1
Summary: Tooling for submitting JSON dumps of Puppet reports to ElasticSearch
Home-page: http://github.com/thrnio/puppet_es
Author: Ryan Whitehurst
Author-email: UNKNOWN
License: Apache License 2.0
Platform: UNKNOWN
Classifier: License :: OSI Approved :: Apache Software License
Requires-Dist: elasticsearch
Requires-Dist: python-dateutil
